Workbook

Sheet Read me
A1: TheraVoca FORECAST MODEL
A2: How to use this workbook
A4: This file models TheraVoca's monthly revenue, COGS, and gross margin across three scenarios:
A5: - Today (pre-launch testing)
A6: - Soft launch (~100 patient intakes / month)
A7: - Growth (~1,000 patient intakes / month)
A9: Edit anything in an AMBER cell on the Assumptions tab; every downstream sheet recomputes via formulas.
A11: Sheets in this workbook:
A13: Assumptions -- inputs (price, conversion %, intakes, per-unit costs, fixed costs)
A14: Revenue Model -- paying therapist count, gross MRR, Stripe fees, net MRR
A15: COGS -- per-vendor monthly cost broken into variable + fixed
A16: P&L Summary -- revenue, COGS, gross profit, gross margin %, unit economics
... A25: Generated 2026-05-18 by Joshua Rosenthal, TheraVoca.

Sheet Assumptions
A1: INPUTS -- EDIT THE AMBER CELLS
A2: TheraVoca Forecast Assumptions
A3: Three scenarios across columns B/C/D. Anything amber is editable; every downstream sheet recomputes from these cells. Excludes paid-ads marketing budget per founder request.
A5: Assumption | B5: Today (pre-launch) | C5: Soft launch | D5: Growth | E5: Notes
A7: Therapist economics
A8: Therapist monthly price ($) | B8: 45 | C8: 45 | D8: 45 | E8: Live in the codebase as $45/mo after a 30-day free trial.
A9: Free-trial length (days) | B9: 30 | C9: 30 | D9: 30 | E9: Trial is 30 days; therapists in trial don't generate revenue.
A10: Active therapists (signed up) | B10: 5 | C10: 50 | D10: 350 | E10: Total therapists with live profiles. Today = real + a few testers.
A11: % in free trial right now | B11: 1 | C11: 0.3 | D11: 0.1 | E11: Higher early on (everyone's new). Lower at scale (most converted long ago).
A12: Trial-to-paid conversion % | B12: 0.55 | C12: 0.6 | D12: 0.65 | E12: What share of trialing therapists convert to a paid sub. Industry-standard early-product range is 40-70%.
A13: -> Paying therapists (computed) | B13: =ROUND(B9*(1-B10)+B9*B10*B11,0) | C13: =ROUND(C9*(1-C10)+C9*C10*C11,0) | D13: =ROUND(D9*(1-D10)+D9*D10*D11,0) | E13: Therapists outside the trial + the converted share of trialing therapists.
A15: Patient demand
A16: Patient intakes per month | B16: 5 | C16: 100 | D16: 1000 | E16: Completed intake submissions. Soft-launch + growth are TheraVoca targets, not industry averages.
A17: Therapists matched per intake | B17: 3 | C17: 3 | D17: 3 | E17: Hard-coded in product today.
A19: Per-unit infrastructure costs
A20: Stripe % fee (per charge) | B20: 0.029 | C20: 0.029 | D20: 0.029 | E20: US card processing fee. Same across scenarios.
A21: Stripe flat fee per charge ($) | B21: 0.3 | C21: 0.3 | D21: 0.3 | E21: Same across scenarios.
A22: Anthropic Claude / paying therapist / mo | B22: 0.1 | C22: 0.1 | D22: 0.12 | E22: Research enrichment warmup + occasional bio drafts. Cached 30 days.
A23: OpenAI embeddings / intake | B23: 2e-05 | C23: 2e-05 | D23: 2e-05 | E23: Patient open-text + deep-match vectors. Trivially small at this token rate.
A24: Video CDN / intake (proxy) | B24: 0.01 | C24: 0.01 | D24: 0.01 | E24: Cloudflare Stream delivery cost. Scales with landing-page traffic; intakes are a rough proxy.
A25: SMS variable / intake | B25: 0.025 | C25: 0.025 | D25: 0.025 | E25: ~5 SMS per match round (alerts to 3 therapists + 2 patient confirms) at $0.005/SMS US.
A26: Email / intake (free tier 0 until 3K/mo) | B26: 0 | C26: 0 | D26: 0.0004 | E26: Resend is free up to 3K/mo. Growth assumes $20/mo / 50K emails.
A28: Fixed costs (don't scale with intakes)
A29: Render hosting (web services) | B29: 7 | C29: 14 | D29: 50 | E29: $7 Starter staging; +$7 prod soft launch; prod upgrades to Standard ($25) at growth.
A30: MongoDB Atlas | B30: 0 | C30: 0 | D30: 57 | E30: M0 free covers today + soft launch. M10 ($57) when storage caps OR when we sign a BAA.
A31: Sentry error tracking | B31: 0 | C31: 0 | D31: 26 | E31: Developer tier free up to 5K errors/mo. Team $26 at growth.
A32: Telnyx SMS (fixed: number + brand + campaign) | B32: 5 | C32: 15 | D32: 25 | E32: Phone number + A2P brand + 10DLC campaign vetting. Higher tier at scale.
A33: Resend (email base plan) | B33: 0 | C33: 0 | D33: 20 | E33: Free up to 3K/mo. $20 for 50K at growth.
A34: Domain (theravoca.com amortized) | B34: 1 | C34: 1 | D34: 1 | E34: ~$12/yr.
A35: Cloudflare Stream storage | B35: 1 | C35: 1 | D35: 1 | E35: 5 testimonial videos stored. Delivery is variable; covered above per-intake.

Sheet Revenue Model
A1: REVENUE
A2: Monthly recurring revenue
A3: All numbers are formulas referencing the Assumptions sheet. Edit Assumptions to recompute.
A5: Line item | B5: Today | C5: Soft launch | D5: Growth | E5: Notes
A7: Paying therapists | B7: =Assumptions!B13 | C7: =Assumptions!C13 | D7: =Assumptions!D13 | E7: From Assumptions sheet: signed-up * (1 - trial%) + trial * conversion%.
A8: Therapist monthly price | B8: =Assumptions!B7 | C8: =Assumptions!C7 | D8: =Assumptions!D7 | E8: From Assumptions.
A9: Gross MRR (therapist subs) | B9: =B7*B8 | C9: =C7*C8 | D9: =D7*D8 | E9: Paying therapists * monthly price.
A10: Stripe fees | B10: =B9*Assumptions!B20+B7*Assumptions!B21 | C10: =C9*Assumptions!C20+C7*Assumptions!C21 | D10: =D9*Assumptions!D20+D7*Assumptions!D21 | E10: 2.9% on gross MRR + $0.30 per charge (one per paying therapist).
A11: Net MRR after Stripe | B11: =B9-B10 | C11: =C9-C10 | D11: =D9-D10 | E11: What lands in the business account each month.

Sheet COGS
A1: COGS
A2: Monthly infrastructure cost
A3: Per-vendor monthly bill. Variable costs scale with intake volume and paying therapists; fixed costs are flat at each scenario tier.
A5: Line item | B5: Today | C5: Soft launch | D5: Growth | E5: Notes
A7: Variable
A8: Anthropic Claude API | B8: =Assumptions!B13*Assumptions!B22 | C8: =Assumptions!C13*Assumptions!C22 | D8: =Assumptions!D13*Assumptions!D22 | E8: Paying therapists * Claude $ per therapist per month (Assumptions).
A9: OpenAI embeddings | B9: =Assumptions!B16*Assumptions!B23 | C9: =Assumptions!C16*Assumptions!C23 | D9: =Assumptions!D16*Assumptions!D23 | E9: Intakes * per-intake embedding cost.
A10: Cloudflare Stream delivery | B10: =Assumptions!B16*Assumptions!B24 | C10: =Assumptions!C16*Assumptions!C24 | D10: =Assumptions!D16*Assumptions!D24 | E10: Approximated by intakes (proxy for landing-page traffic).
A11: Telnyx SMS (variable) | B11: =Assumptions!B16*Assumptions!B25 | C11: =Assumptions!C16*Assumptions!C25 | D11: =Assumptions!D16*Assumptions!D25 | E11: Intakes * ~5 SMS each at US carrier rate.
A12: Resend email (variable) | B12: =Assumptions!B16*Assumptions!B26 | C12: =Assumptions!C16*Assumptions!C26 | D12: =Assumptions!D16*Assumptions!D26 | E12: Free under 3K/mo; growth assumes paid plan.
A13: Subtotal variable | B13: =SUM(B8:B12) | C13: =SUM(C8:C12) | D13: =SUM(D8:D12)
A15: Fixed
A16: Render hosting | B16: =Assumptions!B29 | C16: =Assumptions!C29 | D16: =Assumptions!D29
A17: MongoDB Atlas | B17: =Assumptions!B30 | C17: =Assumptions!C30 | D17: =Assumptions!D30
A18: Sentry | B18: =Assumptions!B31 | C18: =Assumptions!C31 | D18: =Assumptions!D31
A19: Telnyx fixed (number + A2P) | B19: =Assumptions!B32 | C19: =Assumptions!C32 | D19: =Assumptions!D32
A20: Resend base | B20: =Assumptions!B33 | C20: =Assumptions!C33 | D20: =Assumptions!D33
A21: Domain | B21: =Assumptions!B34 | C21: =Assumptions!C34 | D21: =Assumptions!D34
A22: Cloudflare Stream storage | B22: =Assumptions!B35 | C22: =Assumptions!C35 | D22: =Assumptions!D35
A23: Subtotal fixed | B23: =SUM(B16:B22) | C23: =SUM(C16:C22) | D23: =SUM(D16:D22)
A25: TOTAL monthly infrastructure | B25: =B13+B23 | C25: =C13+C23 | D25: =D13+D23

Sheet P&L Summary
A1: P&L -- EXCLUDES PAID-ADS MARKETING
A2: Monthly P&L summary
A3: Revenue - COGS = Gross profit. Paid-ad spend is intentionally NOT in this model -- the founder budgets that separately based on growth targets.
B5: Today | C5: Soft launch | D5: Growth | E5: Notes
A7: Net MRR (after Stripe) | B7: ='Revenue Model'!B11 | C7: ='Revenue Model'!C11 | D7: ='Revenue Model'!D11 | E7: From Revenue Model sheet.
A8: Infrastructure COGS | B8: =COGS!B25 | C8: =COGS!C25 | D8: =COGS!D25 | E8: From COGS sheet.
A9: Gross profit | B9: =B7-B8 | C9: =C7-C8 | D9: =D7-D8 | E9: Net MRR - infrastructure COGS.
A10: Gross margin % | B10: =IF(B7=0,0,B9/B7) | C10: =IF(C7=0,0,C9/C7) | D10: =IF(D7=0,0,D9/D7) | E10: Gross profit / net MRR.
A12: Unit economics
A13: Gross profit per paying therapist | B13: =IF('Revenue Model'!B7=0,0,B9/'Revenue Model'!B7) | C13: =IF('Revenue Model'!C7=0,0,C9/'Revenue Model'!C7) | D13: =IF('Revenue Model'!D7=0,0,D9/'Revenue Model'!D7) | E13: Gross profit / paying therapists. Useful for sizing CAC budget.
A14: COGS per intake | B14: =IF(Assumptions!B16=0,0,B8/Assumptions!B16) | C14: =IF(Assumptions!C16=0,0,C8/Assumptions!C16) | D14: =IF(Assumptions!D16=0,0,D8/Assumptions!D16) | E14: Total COGS divided by intakes. A patient-acquisition cost ceiling on the platform side.

Sheet 12-Month Forecast
A1: 12-MONTH PROJECTION
A2: Monthly trajectory from soft-launch to growth
A3: Straight-line interpolation from soft-launch month-1 toward growth month-12 across two drivers (paying therapists + intakes per month). Cumulative cash columns assume reinvestment-free P&L (excludes paid-ad spend, owner draws, taxes).
A5: Month | B5: Paying therapists | C5: Intakes / mo | D5: Net MRR | E5: Monthly COGS | F5: Monthly gross profit | G5: Cumulative GP
A7: M1 | B7: =ROUND('Revenue Model'!C7+('Revenue Model'!D7-'Revenue Model'!C7)*((1-1)/11),0) | C7: =ROUND(Assumptions!C16+(Assumptions!D16-Assumptions!C16)*((1-1)/11),0) | D7: =B7*Assumptions!D7-(B7*Assumptions!D7*Assumptions!D20+B7*Assumptions!D21) | E7: =B7*Assumptions!D22+C7*(Assumptions!D23+Assumptions!D24+Assumptions!D25+Assumptions!D26)+(Assumptions!C29+Assumptions!C30+Assumptions!C31+Assumptions!C32+Assumptions!C33+Assumptions!C34+Assumptions!C35)+((Assumptions!D29+Assumptions!D30+Assumptions!D31+Assumptions!D32+Assumptions!D33+Assumptions!D34+Assumptions!D35)-(Assumptions!C29+Assumptions!C30+Assumptions!C31+Assumptions!C32+Assumptions!C33+Assumptions!C34+Assumptions!C35))*((1-1)/11) | F7: =D7-E7 | G7: =F7
A8: M2 | B8: =ROUND('Revenue Model'!C7+('Revenue Model'!D7-'Revenue Model'!C7)*((2-1)/11),0) | C8: =ROUND(Assumptions!C16+(Assumptions!D16-Assumptions!C16)*((2-1)/11),0) | D8: =B8*Assumptions!D7-(B8*Assumptions!D7*Assumptions!D20+B8*Assumptions!D21) | E8: =B8*Assumptions!D22+C8*(Assumptions!D23+Assumptions!D24+Assumptions!D25+Assumptions!D26)+(Assumptions!C29+Assumptions!C30+Assumptions!C31+Assumptions!C32+Assumptions!C33+Assumptions!C34+Assumptions!C35)+((Assumptions!D29+Assumptions!D30+Assumptions!D31+Assumptions!D32+Assumptions!D33+Assumptions!D34+Assumptions!D35)-(Assumptions!C29+Assumptions!C30+Assumptions!C31+Assumptions!C32+Assumptions!C33+Assumptions!C34+Assumptions!C35))*((2-1)/11) | F8: =D8-E8 | G8: =G7+F8
A9: M3 | B9: =ROUND('Revenue Model'!C7+('Revenue Model'!D7-'Revenue Model'!C7)*((3-1)/11),0) | C9: =ROUND(Assumptions!C16+(Assumptions!D16-Assumptions!C16)*((3-1)/11),0) | D9: =B9*Assumptions!D7-(B9*Assumptions!D7*Assumptions!D20+B9*Assumptions!D21) | E9: =B9*Assumptions!D22+C9*(Assumptions!D23+Assumptions!D24+Assumptions!D25+Assumptions!D26)+(Assumptions!C29+Assumptions!C30+Assumptions!C31+Assumptions!C32+Assumptions!C33+Assumptions!C34+Assumptions!C35)+((Assumptions!D29+Assumptions!D30+Assumptions!D31+Assumptions!D32+Assumptions!D33+Assumptions!D34+Assumptions!D35)-(Assumptions!C29+Assumptions!C30+Assumptions!C31+Assumptions!C32+Assumptions!C33+Assumptions!C34+Assumptions!C35))*((3-1)/11) | F9: =D9-E9 | G9: =G8+F9
A10: M4 | B10: =ROUND('Revenue Model'!C7+('Revenue Model'!D7-'Revenue Model'!C7)*((4-1)/11),0) | C10: =ROUND(Assumptions!C16+(Assumptions!D16-Assumptions!C16)*((4-1)/11),0) | D10: =B10*Assumptions!D7-(B10*Assumptions!D7*Assumptions!D20+B10*Assumptions!D21) | E10: =B10*Assumptions!D22+C10*(Assumptions!D23+Assumptions!D24+Assumptions!D25+Assumptions!D26)+(Assumptions!C29+Assumptions!C30+Assumptions!C31+Assumptions!C32+Assumptions!C33+Assumptions!C34+Assumptions!C35)+((Assumptions!D29+Assumptions!D30+Assumptions!D31+Assumptions!D32+Assumptions!D33+Assumptions!D34+Assumptions!D35)-(Assumptions!C29+Assumptions!C30+Assumptions!C31+Assumptions!C32+Assumptions!C33+Assumptions!C34+Assumptions!C35))*((4-1)/11) | F10: =D10-E10 | G10: =G9+F10
A11: M5 | B11: =ROUND('Revenue Model'!C7+('Revenue Model'!D7-'Revenue Model'!C7)*((5-1)/11),0) | C11: =ROUND(Assumptions!C16+(Assumptions!D16-Assumptions!C16)*((5-1)/11),0) | D11: =B11*Assumptions!D7-(B11*Assumptions!D7*Assumptions!D20+B11*Assumptions!D21) | E11: =B11*Assumptions!D22+C11*(Assumptions!D23+Assumptions!D24+Assumptions!D25+Assumptions!D26)+(Assumptions!C29+Assumptions!C30+Assumptions!C31+Assumptions!C32+Assumptions!C33+Assumptions!C34+Assumptions!C35)+((Assumptions!D29+Assumptions!D30+Assumptions!D31+Assumptions!D32+Assumptions!D33+Assumptions!D34+Assumptions!D35)-(Assumptions!C29+Assumptions!C30+Assumptions!C31+Assumptions!C32+Assumptions!C33+Assumptions!C34+Assumptions!C35))*((5-1)/11) | F11: =D11-E11 | G11: =G10+F11
A12: M6 | B12: =ROUND('Revenue Model'!C7+('Revenue Model'!D7-'Revenue Model'!C7)*((6-1)/11),0) | C12: =ROUND(Assumptions!C16+(Assumptions!D16-Assumptions!C16)*((6-1)/11),0) | D12: =B12*Assumptions!D7-(B12*Assumptions!D7*Assumptions!D20+B12*Assumptions!D21) | E12: =B12*Assumptions!D22+C12*(Assumptions!D23+Assumptions!D24+Assumptions!D25+Assumptions!D26)+(Assumptions!C29+Assumptions!C30+Assumptions!C31+Assumptions!C32+Assumptions!C33+Assumptions!C34+Assumptions!C35)+((Assumptions!D29+Assumptions!D30+Assumptions!D31+Assumptions!D32+Assumptions!D33+Assumptions!D34+Assumptions!D35)-(Assumptions!C29+Assumptions!C30+Assumptions!C31+Assumptions!C32+Assumptions!C33+Assumptions!C34+Assumptions!C35))*((6-1)/11) | F12: =D12-E12 | G12: =G11+F12
A13: M7 | B13: =ROUND('Revenue Model'!C7+('Revenue Model'!D7-'Revenue Model'!C7)*((7-1)/11),0) | C13: =ROUND(Assumptions!C16+(Assumptions!D16-Assumptions!C16)*((7-1)/11),0) | D13: =B13*Assumptions!D7-(B13*Assumptions!D7*Assumptions!D20+B13*Assumptions!D21) | E13: =B13*Assumptions!D22+C13*(Assumptions!D23+Assumptions!D24+Assumptions!D25+Assumptions!D26)+(Assumptions!C29+Assumptions!C30+Assumptions!C31+Assumptions!C32+Assumptions!C33+Assumptions!C34+Assumptions!C35)+((Assumptions!D29+Assumptions!D30+Assumptions!D31+Assumptions!D32+Assumptions!D33+Assumptions!D34+Assumptions!D35)-(Assumptions!C29+Assumptions!C30+Assumptions!C31+Assumptions!C32+Assumptions!C33+Assumptions!C34+Assumptions!C35))*((7-1)/11) | F13: =D13-E13 | G13: =G12+F13
A14: M8 | B14: =ROUND('Revenue Model'!C7+('Revenue Model'!D7-'Revenue Model'!C7)*((8-1)/11),0) | C14: =ROUND(Assumptions!C16+(Assumptions!D16-Assumptions!C16)*((8-1)/11),0) | D14: =B14*Assumptions!D7-(B14*Assumptions!D7*Assumptions!D20+B14*Assumptions!D21) | E14: =B14*Assumptions!D22+C14*(Assumptions!D23+Assumptions!D24+Assumptions!D25+Assumptions!D26)+(Assumptions!C29+Assumptions!C30+Assumptions!C31+Assumptions!C32+Assumptions!C33+Assumptions!C34+Assumptions!C35)+((Assumptions!D29+Assumptions!D30+Assumptions!D31+Assumptions!D32+Assumptions!D33+Assumptions!D34+Assumptions!D35)-(Assumptions!C29+Assumptions!C30+Assumptions!C31+Assumptions!C32+Assumptions!C33+Assumptions!C34+Assumptions!C35))*((8-1)/11) | F14: =D14-E14 | G14: =G13+F14
A15: M9 | B15: =ROUND('Revenue Model'!C7+('Revenue Model'!D7-'Revenue Model'!C7)*((9-1)/11),0) | C15: =ROUND(Assumptions!C16+(Assumptions!D16-Assumptions!C16)*((9-1)/11),0) | D15: =B15*Assumptions!D7-(B15*Assumptions!D7*Assumptions!D20+B15*Assumptions!D21) | E15: =B15*Assumptions!D22+C15*(Assumptions!D23+Assumptions!D24+Assumptions!D25+Assumptions!D26)+(Assumptions!C29+Assumptions!C30+Assumptions!C31+Assumptions!C32+Assumptions!C33+Assumptions!C34+Assumptions!C35)+((Assumptions!D29+Assumptions!D30+Assumptions!D31+Assumptions!D32+Assumptions!D33+Assumptions!D34+Assumptions!D35)-(Assumptions!C29+Assumptions!C30+Assumptions!C31+Assumptions!C32+Assumptions!C33+Assumptions!C34+Assumptions!C35))*((9-1)/11) | F15: =D15-E15 | G15: =G14+F15
A16: M10 | B16: =ROUND('Revenue Model'!C7+('Revenue Model'!D7-'Revenue Model'!C7)*((10-1)/11),0) | C16: =ROUND(Assumptions!C16+(Assumptions!D16-Assumptions!C16)*((10-1)/11),0) | D16: =B16*Assumptions!D7-(B16*Assumptions!D7*Assumptions!D20+B16*Assumptions!D21) | E16: =B16*Assumptions!D22+C16*(Assumptions!D23+Assumptions!D24+Assumptions!D25+Assumptions!D26)+(Assumptions!C29+Assumptions!C30+Assumptions!C31+Assumptions!C32+Assumptions!C33+Assumptions!C34+Assumptions!C35)+((Assumptions!D29+Assumptions!D30+Assumptions!D31+Assumptions!D32+Assumptions!D33+Assumptions!D34+Assumptions!D35)-(Assumptions!C29+Assumptions!C30+Assumptions!C31+Assumptions!C32+Assumptions!C33+Assumptions!C34+Assumptions!C35))*((10-1)/11) | F16: =D16-E16 | G16: =G15+F16
A17: M11 | B17: =ROUND('Revenue Model'!C7+('Revenue Model'!D7-'Revenue Model'!C7)*((11-1)/11),0) | C17: =ROUND(Assumptions!C16+(Assumptions!D16-Assumptions!C16)*((11-1)/11),0) | D17: =B17*Assumptions!D7-(B17*Assumptions!D7*Assumptions!D20+B17*Assumptions!D21) | E17: =B17*Assumptions!D22+C17*(Assumptions!D23+Assumptions!D24+Assumptions!D25+Assumptions!D26)+(Assumptions!C29+Assumptions!C30+Assumptions!C31+Assumptions!C32+Assumptions!C33+Assumptions!C34+Assumptions!C35)+((Assumptions!D29+Assumptions!D30+Assumptions!D31+Assumptions!D32+Assumptions!D33+Assumptions!D34+Assumptions!D35)-(Assumptions!C29+Assumptions!C30+Assumptions!C31+Assumptions!C32+Assumptions!C33+Assumptions!C34+Assumptions!C35))*((11-1)/11) | F17: =D17-E17 | G17: =G16+F17
A18: M12 | B18: =ROUND('Revenue Model'!C7+('Revenue Model'!D7-'Revenue Model'!C7)*((12-1)/11),0) | C18: =ROUND(Assumptions!C16+(Assumptions!D16-Assumptions!C16)*((12-1)/11),0) | D18: =B18*Assumptions!D7-(B18*Assumptions!D7*Assumptions!D20+B18*Assumptions!D21) | E18: =B18*Assumptions!D22+C18*(Assumptions!D23+Assumptions!D24+Assumptions!D25+Assumptions!D26)+(Assumptions!C29+Assumptions!C30+Assumptions!C31+Assumptions!C32+Assumptions!C33+Assumptions!C34+Assumptions!C35)+((Assumptions!D29+Assumptions!D30+Assumptions!D31+Assumptions!D32+Assumptions!D33+Assumptions!D34+Assumptions!D35)-(Assumptions!C29+Assumptions!C30+Assumptions!C31+Assumptions!C32+Assumptions!C33+Assumptions!C34+Assumptions!C35))*((12-1)/11) | F18: =D18-E18 | G18: =G17+F18
A19: Year 1 | D19: =SUM(D7:D18) | E19: =SUM(E7:E18) | F19: =SUM(F7:F18) | G19: =G18
